mock_data/__init__.py
mock_data/user/__init__.py
tests/__init__.py
utils/FileUtils.py
utils/__init__.py
utils/logger.py
black_tortoise-0.3.dist-info/METADATA
black_tortoise-0.3.dist-info/WHEEL
black_tortoise-0.3.dist-info/top_level.txt
black_tortoise-0.3.dist-info/RECORD
