Metadata-Version: 2.1
Name: black-tortoise
Version: 0.3
Summary: 玄武 SDK 是一个提供底层工具级的项目，类似于hutool 一样，提供很多的工具类
Home-page: https://github.com/lizhen1412/black_tortoise
Author: Lambert
Author-email: 595265454@qq.com
License: LICENSE
Classifier: Development Status :: 3 - Alpha
Classifier: Intended Audience :: Developers
Classifier: License :: OSI Approved :: MIT License
Classifier: Programming Language :: Python :: 3
Classifier: Programming Language :: Python :: 3.6
Classifier: Programming Language :: Python :: 3.7
Classifier: Programming Language :: Python :: 3.8
Requires-Python: >=3.6
Requires-Dist: faker (>=18.10.1)
Requires-Dist: loguru (>=0.7.0)
Requires-Dist: requests (>=2.31.0)
Requires-Dist: gmssl (>=3.2.2)
